[
  {
    "trade_id": "T001",
    "symbol": "RELIANCE.NS",
    "timestamp": "2026-03-27T10:15:00",
    "setup_type": "Breakout_pullback",
    "entry_reasoning": "Broke above 2840 resistance, pulled back with declining volume, bullish divergence on RSI",
    "stop_loss": 2820.00,
    "target": 2910.00,
    "entry_price": 2850.00,
    "planned_entry_price": 2850.00,
    "actual_entry_price": 2850.00,
    "position_size": 100,
    "calculated_position_size": 100,
    "risk_reward_ratio": 3.0,
    "stop_loss_entered": true,
    "exit_price": 2880.00,
    "exit_reason": "Trailing_stop",
    "exit_was_emotional": false,
    "stop_was_respected": true,
    "pnl": 3000.00,
    "lessons_learned": ["Perfect execution of breakout-pullback setup"],
    "mistakes_made": []
  },
  {
    "trade_id": "T002",
    "symbol": "TATAMOTORS.NS",
    "timestamp": "2026-03-27T11:30:00",
    "setup_type": "Reversal",
    "entry_reasoning": "Double bottom at 720, MACD bullish crossover",
    "stop_loss": 715.00,
    "target": 750.00,
    "entry_price": 725.00,
    "planned_entry_price": 720.00,
    "actual_entry_price": 725.00,
    "position_size": 150,
    "calculated_position_size": 150,
    "risk_reward_ratio": 2.5,
    "stop_loss_entered": true,
    "exit_price": 715.00,
    "exit_reason": "Stop_loss",
    "exit_was_emotional": false,
    "stop_was_respected": true,
    "pnl": -1500.00,
    "lessons_learned": ["Wait for confirmation candle before entering reversal"],
    "mistakes_made": ["Entered too early, should have waited for close above 722"]
  },
  {
    "trade_id": "T003",
    "symbol": "TATASTEEL.NS",
    "timestamp": "2026-03-27T14:00:00",
    "setup_type": "Continuation",
    "entry_reasoning": "Strong uptrend, pullback to 20 EMA, volume supporting",
    "stop_loss": 142.00,
    "target": 150.00,
    "entry_price": 144.50,
    "planned_entry_price": 144.50,
    "actual_entry_price": 144.80,
    "position_size": 400,
    "calculated_position_size": 400,
    "risk_reward_ratio": 2.18,
    "stop_loss_entered": true,
    "exit_price": 148.00,
    "exit_reason": "Partial_target",
    "exit_was_emotional": false,
    "stop_was_respected": true,
    "pnl": 1400.00,
    "lessons_learned": [],
    "mistakes_made": []
  }
]
